pxea/__init__.py
pxea/main.py
pxea-1.0.dist-info/DESCRIPTION.rst
pxea-1.0.dist-info/METADATA
pxea-1.0.dist-info/RECORD
pxea-1.0.dist-info/WHEEL
pxea-1.0.dist-info/metadata.json
pxea-1.0.dist-info/top_level.txt
