Metadata-Version: 2.0
Name: pxea
Version: 1.0
Summary: Proximal pathway enrichment analysis
Home-page: http://github.com/emreg00/pxea
Author: Emre Guney
Author-email: emreguney@gmail.com
License: UNKNOWN
Platform: UNKNOWN
Requires-Dist: numpy
Requires-Dist: scipy
Requires-Dist: networkx
